LICENSE
README.md
setup.py
numbers_properties_pkg/__init__.py
numbers_properties_pkg/numbers_properties.py
pkg_Sam_CPP.egg-info/PKG-INFO
pkg_Sam_CPP.egg-info/SOURCES.txt
pkg_Sam_CPP.egg-info/dependency_links.txt
pkg_Sam_CPP.egg-info/top_level.txt