Metadata-Version: 2.1
Name: pkg-Sam-CPP
Version: 0.0.1
Summary: A small example package for my Ideas portal app
Home-page: https://github.com/Sameera23244950/CPP_Library_Samsou
Author: Sam
Author-email: x23244950@student.ncirl.ie
Classifier: Programming Language :: Python :: 3
Classifier: License :: OSI Approved :: MIT License
Classifier: Operating System :: OS Independent
Requires-Python: >=3.6
License-File: LICENSE
